fancyping/__init__.py
fancyping/cmdline.py
fancyping/icmp.py
fancyping/ui.py
fancyping-0.3.0.dist-info/LICENSE
fancyping-0.3.0.dist-info/METADATA
fancyping-0.3.0.dist-info/WHEEL
fancyping-0.3.0.dist-info/entry_points.txt
fancyping-0.3.0.dist-info/top_level.txt
fancyping-0.3.0.dist-info/RECORD
